cropioai_tools/__init__.py
cropioai_tools/adapters/embedchain_adapter.py
cropioai_tools/adapters/lancedb_adapter.py
cropioai_tools/adapters/pdf_embedchain_adapter.py
cropioai_tools/tools/__init__.py
cropioai_tools/tools/ai_mind_tool/README.md
cropioai_tools/tools/ai_mind_tool/__init__.py
cropioai_tools/tools/ai_mind_tool/ai_mind_tool.py
cropioai_tools/tools/brave_search_tool/README.md
cropioai_tools/tools/brave_search_tool/__init__.py
cropioai_tools/tools/brave_search_tool/brave_search_tool.py
cropioai_tools/tools/browserbase_load_tool/README.md
cropioai_tools/tools/browserbase_load_tool/browserbase_load_tool.py
cropioai_tools/tools/code_docs_search_tool/README.md
cropioai_tools/tools/code_docs_search_tool/code_docs_search_tool.py
cropioai_tools/tools/code_interpreter_tool/Dockerfile
cropioai_tools/tools/code_interpreter_tool/README.md
cropioai_tools/tools/code_interpreter_tool/code_interpreter_tool.py
cropioai_tools/tools/composio_tool/README.md
cropioai_tools/tools/composio_tool/composio_tool.py
cropioai_tools/tools/csv_search_tool/README.md
cropioai_tools/tools/csv_search_tool/csv_search_tool.py
cropioai_tools/tools/dalle_tool/README.MD
cropioai_tools/tools/dalle_tool/dalle_tool.py
cropioai_tools/tools/directory_read_tool/README.md
cropioai_tools/tools/directory_read_tool/directory_read_tool.py
cropioai_tools/tools/directory_search_tool/README.md
cropioai_tools/tools/directory_search_tool/directory_search_tool.py
cropioai_tools/tools/docx_search_tool/README.md
cropioai_tools/tools/docx_search_tool/docx_search_tool.py
cropioai_tools/tools/exa_tools/README.md
cropioai_tools/tools/exa_tools/exa_base_tool.py
cropioai_tools/tools/exa_tools/exa_search_tool.py
cropioai_tools/tools/file_read_tool/README.md
cropioai_tools/tools/file_read_tool/file_read_tool.py
cropioai_tools/tools/file_writer_tool/README.md
cropioai_tools/tools/file_writer_tool/file_writer_tool.py
cropioai_tools/tools/firecrawl_crawl_website_tool/README.md
cropioai_tools-0.0.16.dist-info/METADATA
cropioai_tools-0.0.16.dist-info/WHEEL
cropioai_tools-0.0.16.dist-info/licenses/LICENSE
cropioai_tools-0.0.16.dist-info/RECORD
