Metadata-Version: 2.4
Name: cropioai-tools
Version: 0.0.16
Summary: Set of tools for the cropioAI framework
Project-URL: Homepage, https://cropio.in
Project-URL: Repository, https://github.com/cropioAIInc/cropioAI-tools
Project-URL: Documentation, https://docs.cropio.in
Author-email: Cropio <cropioindia@gmail.com>
License-File: LICENSE
Requires-Python: <=3.13,>=3.10
Requires-Dist: chromadb>=0.4.22
Requires-Dist: click>=8.1.8
Requires-Dist: cropioai>=0.2.0
Requires-Dist: docker>=7.1.0
Requires-Dist: embedchain>=0.1.114
Requires-Dist: lancedb>=0.5.4
Requires-Dist: openai>=1.12.0
Requires-Dist: pydantic>=2.6.1
Requires-Dist: pyright>=1.1.350
Requires-Dist: pytube>=15.0.0
Requires-Dist: requests>=2.31.0
Provides-Extra: beautifulsoup4
Requires-Dist: beautifulsoup4>=4.12.3; extra == 'beautifulsoup4'
Provides-Extra: browserbase
Requires-Dist: browserbase>=1.0.5; extra == 'browserbase'
Provides-Extra: composio-core
Requires-Dist: composio-core>=0.6.11.post1; extra == 'composio-core'
Provides-Extra: firecrawl-py
Requires-Dist: firecrawl-py>=1.8.0; extra == 'firecrawl-py'
Provides-Extra: hyperbrowser
Requires-Dist: hyperbrowser>=0.18.0; extra == 'hyperbrowser'
Provides-Extra: linkup-sdk
Requires-Dist: linkup-sdk>=0.2.2; extra == 'linkup-sdk'
Provides-Extra: multion
Requires-Dist: multion>=1.1.0; extra == 'multion'
Provides-Extra: patronus
Requires-Dist: patronus>=0.0.16; extra == 'patronus'
Provides-Extra: scrapegraph-py
Requires-Dist: scrapegraph-py>=1.9.0; extra == 'scrapegraph-py'
Provides-Extra: scrapfly-sdk
Requires-Dist: scrapfly-sdk>=0.8.19; extra == 'scrapfly-sdk'
Provides-Extra: selenium
Requires-Dist: selenium>=4.27.1; extra == 'selenium'
Provides-Extra: serpapi
Requires-Dist: serpapi>=0.1.5; extra == 'serpapi'
Provides-Extra: snowflake
Requires-Dist: cryptography>=43.0.3; extra == 'snowflake'
Requires-Dist: snowflake-connector-python>=3.12.4; extra == 'snowflake'
Requires-Dist: snowflake-sqlalchemy>=1.7.3; extra == 'snowflake'
Provides-Extra: spider-client
Requires-Dist: spider-client>=0.1.25; extra == 'spider-client'
Provides-Extra: sqlalchemy
Requires-Dist: sqlalchemy>=2.0.35; extra == 'sqlalchemy'
Provides-Extra: weaviate-client
Requires-Dist: weaviate-client>=4.10.2; extra == 'weaviate-client'
